setup.py
customcontent/__init__.py
customcontent/admin.py
customcontent/decorators.py
customcontent/middleware.py
customcontent/models.py
customcontent/templatetags/__init__.py
customcontent/templatetags/customcontent_tags.py
django_customcontent.egg-info/PKG-INFO
django_customcontent.egg-info/SOURCES.txt
django_customcontent.egg-info/dependency_links.txt
django_customcontent.egg-info/top_level.txt