Metadata-Version: 1.0
Name: django-customcontent
Version: 0.2.2
Summary: A django app to allow users to add css/js/html chunks to a page based on the request.path
Home-page: https://github.com/jaymzcd/django-customcontent
Author: Jaymz Campbell
Author-email: jaymz@jaymz.eu
License: UNKNOWN
Platform: UNKNOWN
